WeightConverter/__init__.py
WeightConverter/grams2kilograms.py
WeightConverter/grams2pounds.py
WeightConverter/kilograms2grams.py
WeightConverter/kilograms2pounds.py
WeightConverter/pounds2grams.py
WeightConverter/pounds2kilograms.py
WeightConverter-9.1.dist-info/LICENSE
WeightConverter-9.1.dist-info/METADATA
WeightConverter-9.1.dist-info/WHEEL
WeightConverter-9.1.dist-info/top_level.txt
WeightConverter-9.1.dist-info/RECORD
